[
  {
    "filename": "Learn-About-HTTP-And-HTTPS.md",
    "created": "2025-02-06T14:40:33-03:00"
  },
  {
    "filename": "Package-Managers.md",
    "created": "2025-02-06T12:03:41-03:00"
  },
  {
    "filename": "Comparing-Different-Ways-to-Pass-Strings.md",
    "created": "2025-02-04T13:39:01-03:00"
  },
  {
    "filename": "Understand-about-Buffer.md",
    "created": "2025-02-03T14:56:05-03:00"
  },
  {
    "filename": "Chunks-in-streaming.md",
    "created": "2025-02-03T12:50:10-03:00"
  },
  {
    "filename": "Starting-with-iostream-library.md",
    "created": "2025-02-03T12:22:28-03:00"
  }
]